[
    {
        "name": "Flask",
        "link": "https://flask.palletsprojects.com/",
        "style": "flat",
        "logo": "flask",
        "background_color": "000000",
        "logo_color": "white"
    },
    {
        "name": "FastAPI",
        "link": "https://fastapi.tiangolo.com/",
        "style": "flat",
        "logo": "fastapi",
        "background_color": "009688",
        "logo_color": "white"
    },
    {
        "name": "Django",
        "link": "https://www.djangoproject.com/",
        "style": "flat",
        "logo": "django",
        "background_color": "092E20",
        "logo_color": "white"
    },
    {
        "name": "NodeJS",
        "link": "https://nodejs.org/",
        "style": "flat",
        "logo": "node.js",
        "background_color": "339933",
        "logo_color": "white"
    },
    {
        "name": "Apache Spark",
        "link": "https://spark.apache.org/",
        "style": "flat",
        "logo": "apachespark",
        "background_color": "E25A1C",
        "logo_color": "white"
    },
    {
        "name": "Dagster",
        "link": "https://dagster.io/",
        "style": "flat",
        "logo": "dagster",
        "background_color": "4339BE",
        "logo_color": "white"
    },
    {
        "name": "Airflow",
        "link": "https://airflow.apache.org/",
        "style": "flat",
        "logo": "airflow",
        "background_color": "E43921",
        "logo_color": "white"
    }
]
